odoo/addons/purchase_invoice_plan/README.rst
odoo/addons/purchase_invoice_plan/__init__.py
odoo/addons/purchase_invoice_plan/__manifest__.py
odoo/addons/purchase_invoice_plan/data/purchase_data.xml
odoo/addons/purchase_invoice_plan/i18n/purchase_invoice_plan.pot
odoo/addons/purchase_invoice_plan/models/__init__.py
odoo/addons/purchase_invoice_plan/models/purchase.py
odoo/addons/purchase_invoice_plan/readme/CONTRIBUTORS.rst
odoo/addons/purchase_invoice_plan/readme/DESCRIPTION.rst
odoo/addons/purchase_invoice_plan/readme/USAGE.rst
odoo/addons/purchase_invoice_plan/security/ir.model.access.csv
odoo/addons/purchase_invoice_plan/static/description/icon.png
odoo/addons/purchase_invoice_plan/static/description/index.html
odoo/addons/purchase_invoice_plan/tests/__init__.py
odoo/addons/purchase_invoice_plan/tests/test_purchase_invoice_plan.py
odoo/addons/purchase_invoice_plan/views/purchase_view.xml
odoo/addons/purchase_invoice_plan/wizard/__init__.py
odoo/addons/purchase_invoice_plan/wizard/purchase_create_invoice_plan.py
odoo/addons/purchase_invoice_plan/wizard/purchase_create_invoice_plan_view.xml
odoo/addons/purchase_invoice_plan/wizard/purchase_make_planned_invoice.py
odoo/addons/purchase_invoice_plan/wizard/purchase_make_planned_invoice_view.xml
odoo14_addon_purchase_invoice_plan-14.0.1.3.1.dist-info/METADATA
odoo14_addon_purchase_invoice_plan-14.0.1.3.1.dist-info/WHEEL
odoo14_addon_purchase_invoice_plan-14.0.1.3.1.dist-info/top_level.txt
odoo14_addon_purchase_invoice_plan-14.0.1.3.1.dist-info/RECORD
