Metadata-Version: 2.1
Name: odoo14-addon-purchase-invoice-plan
Version: 14.0.1.3.1
Summary: Add to purchases order, ability to manage future invoice plan
Home-page: https://github.com/OCA/purchase-workflow
Author: Ecosoft,Odoo Community Association (OCA)
Author-email: support@odoo-community.org
License: AGPL-3
Platform: UNKNOWN
Classifier: Programming Language :: Python
Classifier: Framework :: Odoo
Classifier: Framework :: Odoo :: 14.0
Classifier: License :: OSI Approved :: GNU Affero General Public License v3
Classifier: Development Status :: 3 - Alpha
Requires-Python: >=3.6
Requires-Dist: odoo14-addon-purchase-open-qty
Requires-Dist: odoo (<14.1dev,>=14.0a)
